socketio_v4/__init__.py
socketio_v4/asgi.py
socketio_v4/asyncio_aiopika_manager.py
socketio_v4/asyncio_client.py
socketio_v4/asyncio_manager.py
socketio_v4/asyncio_namespace.py
socketio_v4/asyncio_pubsub_manager.py
socketio_v4/asyncio_redis_manager.py
socketio_v4/asyncio_server.py
socketio_v4/base_manager.py
socketio_v4/client.py
socketio_v4/exceptions.py
socketio_v4/kafka_manager.py
socketio_v4/kombu_manager.py
socketio_v4/middleware.py
socketio_v4/namespace.py
socketio_v4/packet.py
socketio_v4/pubsub_manager.py
socketio_v4/redis_manager.py
socketio_v4/server.py
socketio_v4/tornado.py
socketio_v4/zmq_manager.py
python_socketio_v4-4.6.1.dist-info/LICENSE
python_socketio_v4-4.6.1.dist-info/METADATA
python_socketio_v4-4.6.1.dist-info/WHEEL
python_socketio_v4-4.6.1.dist-info/top_level.txt
python_socketio_v4-4.6.1.dist-info/RECORD
